athena/__init__.py
athena/bootstrap/__init__.py
athena/bootstrap/sitecustomize.py
athena/config/__init__.py
athena/config/config.py
athena/config/defaults.py
athena/metrics/__init__.py
athena/metrics/collector.py
athena/patch/__init__.py
athena/patch/main.py
athena/patch/pandas.py
athena/patch/sklearn.py
athena/patch/statsd_config.py
athena/patch/subprocess.py
athena/readers/__init__.py
athena/readers/directory.py
athena/scripts/athena_run.py
athena/tracing/__init__.py
athena/tracing/client.py
athena/tracing/config.py
athena/tracing/headless_extension.py
athena/tracing/local_context.py
athena_run-0.1.50.dist-info/METADATA
athena_run-0.1.50.dist-info/WHEEL
athena_run-0.1.50.dist-info/entry_points.txt
athena_run-0.1.50.dist-info/top_level.txt
athena_run-0.1.50.dist-info/RECORD
